vlcishared/__init__.py
vlcishared/arcgis/arcgis_geoportal_client.py
vlcishared/arcgis/arcgis_geoportal_config.py
vlcishared/csv/generador_csv.py
vlcishared/db/__init__.py
vlcishared/db/mongodb.py
vlcishared/db/oracle.py
vlcishared/db/postgresql.py
vlcishared/db/sqlserver.py
vlcishared/env_variables/__init__.py
vlcishared/env_variables/config.py
vlcishared/env_variables/secrets.py
vlcishared/excepciones/excepciones.py
vlcishared/files/utilidades_ficheros.py
vlcishared/flow/__init__.py
vlcishared/flow/flow.py
vlcishared/ftp/__init__.py
vlcishared/ftp/ftp.py
vlcishared/http/http.py
vlcishared/logging/__init__.py
vlcishared/logging/setup.py
vlcishared/mail/__init__.py
vlcishared/mail/mail_sender.py
vlcishared/mail/mail_server.py
vlcishared/payload/generador_payload.py
vlcishared/sftp/__init__.py
vlcishared/sftp/sftp.py
vlcishared/tests/fixtures/__init__.py
vlcishared/tests/fixtures/arcgis/arcgis.py
vlcishared/tests/fixtures/csv/generador_csv.py
vlcishared/tests/fixtures/db/gestion_fechas.py
vlcishared/tests/fixtures/db/oracle.py
vlcishared/tests/fixtures/db/postgresql.py
vlcishared/tests/fixtures/db/schema_utils.py
vlcishared/tests/fixtures/db/sqlserver.py
vlcishared/tests/fixtures/flow/flow_control.py
vlcishared/tests/fixtures/ftp/ftp.py
vlcishared/tests/fixtures/ftp/sftp.py
vlcishared/tests/fixtures/http/http.py
vlcishared/tests/fixtures/iot/authManager.py
vlcishared/tests/fixtures/iot/cb.py
vlcishared/tests/fixtures/iot/iotaManager.py
vlcishared/tests/fixtures/librerias/datetime.py
vlcishared/tests/fixtures/mail/mail.py
vlcishared/tests/fixtures/os/os.py
vlcishared/tests/fixtures/system/sys_exit.py
vlcishared/tests/utils/terminacion_programas.py
vlcishared/tests/utils/validacion_datos.py
vlcishared/tokens/arcgis_token_provider.py
vlcishared/tokens/arcgis_token_provider_config.py
vlcishared/tokens/token_handler.py
vlcishared/tokens/token_provider.py
vlcishared/utils/__init__.py
vlcishared/utils/context_broker_format.py
vlcishared/utils/date_format.py
vlcishared-23.3.0.dist-info/LICENSE
vlcishared-23.3.0.dist-info/METADATA
vlcishared-23.3.0.dist-info/WHEEL
vlcishared-23.3.0.dist-info/RECORD
