Metadata-Version: 2.1
Name: vlcishared
Version: 23.3.0
Summary: Funciones comúnes a las ETLs del proyecto Valencia smart city
Author: Equipo de integración Valencia smart city
Author-email: integracionvlci@valencia.es
Requires-Python: >=3.12,<4.0
Classifier: Programming Language :: Python :: 3
Classifier: Programming Language :: Python :: 3.12
Classifier: Programming Language :: Python :: 3.13
Requires-Dist: infisicalsdk (>=1.0.3,<2.0.0)
Requires-Dist: oracledb (>=2.3.0,<3.0.0)
Requires-Dist: pandas (>=2.0.3,<3.0.0)
Requires-Dist: paramiko (>=4.0.0,<5.0.0)
Requires-Dist: psycopg2-binary (>=2.9.9,<3.0.0)
Requires-Dist: pymongo (>=4.8.0,<5.0.0)
Requires-Dist: pyodbc (>=5.2.0,<6.0.0)
Requires-Dist: pytest-postgresql (>=7.0.2,<8.0.0)
Requires-Dist: responses (>=0.25.8,<0.26.0)
Requires-Dist: sqlalchemy (>=2.0.31,<3.0.0)
